{"WaitingForReviewer": 3, "WaitingForSubmitter": 10, "abandoned": 12, "abandoned_30": 0, "abandoned_365": 5, "abandoned_7": 0, "approved": 0, "closed": 460, "codereview": 505, "diff_netabandoned_30": -1, "diff_netabandoned_365": -2, "diff_netabandoned_7": 0, "diff_netmerged_30": -1, "diff_netmerged_365": -156, "diff_netmerged_7": 3, "diff_netpending_30": 1, "diff_netpending_365": 0, "diff_netpending_7": 1, "diff_netsubmitted_30": -1, "diff_netsubmitted_365": -158, "diff_netsubmitted_7": 4, "inprogress": 0, "merged": 448, "merged_30": 8, "merged_365": 146, "merged_7": 4, "new": 8, "opened": 8, "pending": 8, "pending_30": 1, "pending_365": 4, "pending_7": 1, "percentage_abandoned_30": 100, "percentage_abandoned_365": 28, "percentage_abandoned_7": 0, "percentage_merged_30": 11, "percentage_merged_365": 51, "percentage_merged_7": 300, "percentage_pending_30": 0, "percentage_pending_365": 0, "percentage_pending_7": 0, "percentage_submitted_30": 9, "percentage_submitted_365": 50, "percentage_submitted_7": 400, "review_time_days_avg": 222.73238969072165, "review_time_days_median": 302.8704, "reviewers": 55, "sent": 448, "submitted": 468, "submitted_30": 9, "submitted_365": 155, "submitted_7": 5, "verified": 595}